[
  {
    "type": "NBA",
    "time": "2023-11-15 08:00:00+0800",
    "match_name": "Pistons vs Hawks",
    "team1": "Pistons",
    "team2": "Hawks",
    "main_bet_list": [
      { "name": "Pistons Winner", "odds": 2.43 },
      { "name": "Hawks Winner", "odds": 1.48 }
    ],
    "more_bet_list": [
      { "name": "Pistons +4", "odds": 1.86 },
      { "name": "Hawks -4", "odds": 2.0 },
      { "name": "Pistons +4.5", "odds": 1.93 },
      { "name": "Hawks -4.5", "odds": 1.93 },
      { "name": "Pistons +5", "odds": 2.0 },
      { "name": "Hawks -5", "odds": 1.86 },
      { "name": "Over 232.5", "odds": 1.87 },
      { "name": "Under 232.5", "odds": 1.97 },
      { "name": "Over 233", "odds": 1.92 },
      { "name": "Under 233", "odds": 1.92 },
      { "name": "Over 233.5", "odds": 1.97 },
      { "name": "Under 233.5", "odds": 1.87 }
    ]
  },
  {
    "type": "NBA",
    "time": "2023-11-15 08:00:00+0800",
    "match_name": "Hornets vs Heat",
    "team1": "Hornets",
    "team2": "Heat",
    "main_bet_list": [
      { "name": "Hornets Winner", "odds": 2.43 },
      { "name": "Heat Winner", "odds": 1.48 }
    ],
    "more_bet_list": [
      { "name": "Hornets +3", "odds": 2.04 },
      { "name": "Heat -3", "odds": 1.82 },
      { "name": "Hornets +3.5", "odds": 1.97 },
      { "name": "Heat -3.5", "odds": 1.89 },
      { "name": "Hornets +4", "odds": 1.9 },
      { "name": "Heat -4", "odds": 1.96 },
      { "name": "Over 225", "odds": 1.9 },
      { "name": "Under 225", "odds": 1.94 },
      { "name": "Over 225.5", "odds": 1.95 },
      { "name": "Under 225.5", "odds": 1.89 },
      { "name": "Over 226", "odds": 2.0 },
      { "name": "Under 226", "odds": 1.84 }
    ]
  },
  {
    "type": "NBA",
    "time": "2023-11-15 08:00:00+0800",
    "match_name": "76ers vs Pacers",
    "team1": "76ers",
    "team2": "Pacers",
    "main_bet_list": [
      { "name": "76ers Winner", "odds": 1.43 },
      { "name": "Pacers Winner", "odds": 2.55 }
    ],
    "more_bet_list": [
      { "name": "76ers -5", "odds": 1.78 },
      { "name": "Pacers +5", "odds": 2.08 },
      { "name": "76ers -5.5", "odds": 1.85 },
      { "name": "Pacers +5.5", "odds": 2.01 },
      { "name": "76ers -6", "odds": 1.92 },
      { "name": "Pacers +6", "odds": 1.94 },
      { "name": "Over 240", "odds": 1.87 },
      { "name": "Under 240", "odds": 1.97 },
      { "name": "Over 240.5", "odds": 1.92 },
      { "name": "Under 240.5", "odds": 1.92 },
      { "name": "Over 241", "odds": 1.97 },
      { "name": "Under 241", "odds": 1.87 }
    ]
  },
  {
    "type": "NBA",
    "time": "2023-11-15 08:30:00+0800",
    "match_name": "Thunder vs Spurs",
    "team1": "Thunder",
    "team2": "Spurs",
    "main_bet_list": [
      { "name": "Thunder Winner", "odds": 1.22 },
      { "name": "Spurs Winner", "odds": 3.31 }
    ],
    "more_bet_list": [
      { "name": "Thunder -8.5", "odds": 1.86 },
      { "name": "Spurs +8.5", "odds": 2.0 },
      { "name": "Thunder -9", "odds": 1.93 },
      { "name": "Spurs +9", "odds": 1.93 },
      { "name": "Thunder -9.5", "odds": 2.0 },
      { "name": "Spurs +9.5", "odds": 1.86 },
      { "name": "Over 237", "odds": 1.87 },
      { "name": "Under 237", "odds": 1.97 },
      { "name": "Over 237.5", "odds": 1.92 },
      { "name": "Under 237.5", "odds": 1.92 },
      { "name": "Over 238", "odds": 1.97 },
      { "name": "Under 238", "odds": 1.87 }
    ]
  },
  {
    "type": "NBA",
    "time": "2023-11-15 08:30:00+0800",
    "match_name": "Nets vs Magic",
    "team1": "Nets",
    "team2": "Magic",
    "main_bet_list": [
      { "name": "Nets Winner", "odds": 1.74 },
      { "name": "Magic Winner", "odds": 2.04 }
    ],
    "more_bet_list": [
      { "name": "Nets -2", "odds": 1.8 },
      { "name": "Magic +2", "odds": 2.06 },
      { "name": "Nets -2.5", "odds": 1.87 },
      { "name": "Magic +2.5", "odds": 1.99 },
      { "name": "Nets -3", "odds": 1.94 },
      { "name": "Magic +3", "odds": 1.92 },
      { "name": "Over 217", "odds": 1.89 },
      { "name": "Under 217", "odds": 1.95 },
      { "name": "Over 217.5", "odds": 1.94 },
      { "name": "Under 217.5", "odds": 1.9 },
      { "name": "Over 218", "odds": 1.99 },
      { "name": "Under 218", "odds": 1.85 }
    ]
  },
  {
    "type": "NBA",
    "time": "2023-11-15 09:00:00+0800",
    "match_name": "Pelicans vs Mavericks",
    "team1": "Pelicans",
    "team2": "Mavericks",
    "main_bet_list": [
      { "name": "Pelicans Winner", "odds": 2.3 },
      { "name": "Mavericks Winner", "odds": 1.55 }
    ],
    "more_bet_list": [
      { "name": "Pelicans +3", "odds": 2.05 },
      { "name": "Mavericks -3", "odds": 1.81 },
      { "name": "Pelicans +3.5", "odds": 1.98 },
      { "name": "Mavericks -3.5", "odds": 1.88 },
      { "name": "Pelicans +4", "odds": 1.91 },
      { "name": "Mavericks -4", "odds": 1.95 },
      { "name": "Over 239.5", "odds": 1.87 },
      { "name": "Under 239.5", "odds": 1.97 },
      { "name": "Over 240", "odds": 1.92 },
      { "name": "Under 240", "odds": 1.92 },
      { "name": "Over 240.5", "odds": 1.97 },
      { "name": "Under 240.5", "odds": 1.87 }
    ]
  },
  {
    "type": "NBA",
    "time": "2023-11-15 10:00:00+0800",
    "match_name": "Jazz vs Trail Blazers",
    "team1": "Jazz",
    "team2": "Trail Blazers",
    "main_bet_list": [
      { "name": "Jazz Winner", "odds": 1.36 },
      { "name": "Trail Blazers Winner", "odds": 2.74 }
    ],
    "more_bet_list": [
      { "name": "Jazz -6.5", "odds": 1.86 },
      { "name": "Trail Blazers +6.5", "odds": 2.0 },
      { "name": "Jazz -7", "odds": 1.93 },
      { "name": "Trail Blazers +7", "odds": 1.93 },
      { "name": "Jazz -7.5", "odds": 2.0 },
      { "name": "Trail Blazers +7.5", "odds": 1.86 },
      { "name": "Over 229", "odds": 1.87 },
      { "name": "Under 229", "odds": 1.97 },
      { "name": "Over 229.5", "odds": 1.92 },
      { "name": "Under 229.5", "odds": 1.92 },
      { "name": "Over 230", "odds": 1.97 },
      { "name": "Under 230", "odds": 1.87 }
    ]
  },
  {
    "type": "NBA",
    "time": "2023-11-15 11:00:00+0800",
    "match_name": "Warriors vs Timberwolves",
    "team1": "Warriors",
    "team2": "Timberwolves",
    "main_bet_list": [
      { "name": "Warriors Winner", "odds": 1.75 },
      { "name": "Timberwolves Winner", "odds": 2.03 }
    ],
    "more_bet_list": [
      { "name": "Warriors -1.5", "odds": 1.86 },
      { "name": "Timberwolves +1.5", "odds": 2.0 },
      { "name": "Warriors -2", "odds": 1.93 },
      { "name": "Timberwolves +2", "odds": 1.93 },
      { "name": "Warriors -2.5", "odds": 2.0 },
      { "name": "Timberwolves +2.5", "odds": 1.86 },
      { "name": "Over 222", "odds": 1.86 },
      { "name": "Under 222", "odds": 1.98 },
      { "name": "Over 222.5", "odds": 1.91 },
      { "name": "Under 222.5", "odds": 1.93 },
      { "name": "Over 223", "odds": 1.96 },
      { "name": "Under 223", "odds": 1.88 }
    ]
  },
  {
    "type": "NBA",
    "time": "2023-11-15 11:00:00+0800",
    "match_name": "Nuggets vs Clippers",
    "team1": "Nuggets",
    "team2": "Clippers",
    "main_bet_list": [
      { "name": "Nuggets Winner", "odds": 1.45 },
      { "name": "Clippers Winner", "odds": 2.5 }
    ],
    "more_bet_list": [
      { "name": "Nuggets -5.5", "odds": 1.86 },
      { "name": "Clippers +5.5", "odds": 2.0 },
      { "name": "Nuggets -6", "odds": 1.93 },
      { "name": "Clippers +6", "odds": 1.93 },
      { "name": "Nuggets -6.5", "odds": 2.0 },
      { "name": "Clippers +6.5", "odds": 1.86 },
      { "name": "Over 222", "odds": 1.87 },
      { "name": "Under 222", "odds": 1.97 },
      { "name": "Over 222.5", "odds": 1.92 },
      { "name": "Under 222.5", "odds": 1.92 },
      { "name": "Over 223", "odds": 1.97 },
      { "name": "Under 223", "odds": 1.87 }
    ]
  },
  {
    "type": "NBA",
    "time": "2023-11-15 11:30:00+0800",
    "match_name": "Lakers vs Grizzlies",
    "team1": "Lakers",
    "team2": "Grizzlies",
    "main_bet_list": [
      { "name": "Lakers Winner", "odds": 1.45 },
      { "name": "Grizzlies Winner", "odds": 2.5 }
    ],
    "more_bet_list": [
      { "name": "Lakers -4.5", "odds": 1.86 },
      { "name": "Grizzlies +4.5", "odds": 2.0 },
      { "name": "Lakers -5", "odds": 1.93 },
      { "name": "Grizzlies +5", "odds": 1.93 },
      { "name": "Lakers -5.5", "odds": 2.0 },
      { "name": "Grizzlies +5.5", "odds": 1.86 },
      { "name": "Over 226", "odds": 1.87 },
      { "name": "Under 226", "odds": 1.97 },
      { "name": "Over 226.5", "odds": 1.92 },
      { "name": "Under 226.5", "odds": 1.92 },
      { "name": "Over 227", "odds": 1.97 },
      { "name": "Under 227", "odds": 1.87 }
    ]
  },
  {
    "type": "NBA",
    "time": "2023-11-02 09:00:00+0800",
    "match_name": "Thunder vs Hawks",
    "team1": "Thunder",
    "team2": "Hawks",
    "main_bet_list": [
      { "name": "Thunder Winner", "odds": 1.77 },
      { "name": "Hawks Winner", "odds": 2.03 }
    ],
    "more_bet_list": [
      { "name": "Thunder -1.5", "odds": 1.87 },
      { "name": "Hawks +1.5", "odds": 2.01 },
      { "name": "Thunder -2", "odds": 1.94 },
      { "name": "Hawks +2", "odds": 1.94 },
      { "name": "Thunder -2.5", "odds": 2.01 },
      { "name": "Hawks +2.5", "odds": 1.87 },
      { "name": "Over 224.5", "odds": 1.91 },
      { "name": "Under 224.5", "odds": 1.95 },
      { "name": "Over 225", "odds": 1.96 },
      { "name": "Under 225", "odds": 1.9 },
      { "name": "Over 225.5", "odds": 2.01 },
      { "name": "Under 225.5", "odds": 1.85 }
    ]
  },
  {
    "type": "NBA",
    "time": "2023-11-02 10:00:00+0800",
    "match_name": "Nuggets vs Pelicans",
    "team1": "Nuggets",
    "team2": "Pelicans",
    "main_bet_list": [
      { "name": "Nuggets Winner", "odds": 1.46 },
      { "name": "Pelicans Winner", "odds": 2.51 }
    ],
    "more_bet_list": [
      { "name": "Nuggets -5", "odds": 1.83 },
      { "name": "Pelicans +5", "odds": 2.05 },
      { "name": "Nuggets -5.5", "odds": 1.9 },
      { "name": "Pelicans +5.5", "odds": 1.98 },
      { "name": "Nuggets -6", "odds": 1.97 },
      { "name": "Pelicans +6", "odds": 1.91 },
      { "name": "Over 226", "odds": 1.88 },
      { "name": "Under 226", "odds": 1.98 },
      { "name": "Over 226.5", "odds": 1.93 },
      { "name": "Under 226.5", "odds": 1.93 },
      { "name": "Over 227", "odds": 1.98 },
      { "name": "Under 227", "odds": 1.88 }
    ]
  },
  {
    "type": "NBA",
    "time": "2023-11-02 10:00:00+0800",
    "match_name": "Warriors vs Kings",
    "team1": "Warriors",
    "team2": "Kings",
    "main_bet_list": [
      { "name": "Warriors Winner", "odds": 1.35 },
      { "name": "Kings Winner", "odds": 2.81 }
    ],
    "more_bet_list": [
      { "name": "Warriors -6.5", "odds": 1.83 },
      { "name": "Kings +6.5", "odds": 2.05 },
      { "name": "Warriors -7", "odds": 1.9 },
      { "name": "Kings +7", "odds": 1.98 },
      { "name": "Warriors -7.5", "odds": 1.97 },
      { "name": "Kings +7.5", "odds": 1.91 },
      { "name": "Over 229", "odds": 1.95 },
      { "name": "Under 229", "odds": 1.91 },
      { "name": "Over 229.5", "odds": 2.0 },
      { "name": "Under 229.5", "odds": 1.86 },
      { "name": "Over 230", "odds": 2.05 },
      { "name": "Under 230", "odds": 1.81 }
    ]
  }
]
