[
  {
    "type": "NBA",
    "time": "2024-03-01 08:00:00+0800",
    "match_name": "Pistons vs Cavaliers",
    "team1": "Pistons",
    "team2": "Cavaliers",
    "main_bet_list": [
      { "name": "Pistons Winner", "odds": 0 },
      { "name": "Cavaliers Winner", "odds": 0 }
    ],
    "more_bet_list": [
      { "name": "Pistons +11", "odds": 2.09 },
      { "name": "Cavaliers -11", "odds": 1.79 },
      { "name": "Pistons +11.5", "odds": 2.0 },
      { "name": "Cavaliers -11.5", "odds": 1.88 },
      { "name": "Pistons +12", "odds": 1.93 },
      { "name": "Cavaliers -12", "odds": 1.95 },
      { "name": "Over 217", "odds": 1.85 },
      { "name": "Under 217", "odds": 2.01 },
      { "name": "Over 217.5", "odds": 1.9 },
      { "name": "Under 217.5", "odds": 1.96 },
      { "name": "Over 218", "odds": 1.95 },
      { "name": "Under 218", "odds": 1.91 }
    ]
  },
  {
    "type": "NBA",
    "time": "2024-03-01 08:00:00+0800",
    "match_name": "76ers vs Hornets",
    "team1": "76ers",
    "team2": "Hornets",
    "main_bet_list": [
      { "name": "76ers Winner", "odds": 1.38 },
      { "name": "Hornets Winner", "odds": 2.72 }
    ],
    "more_bet_list": [
      { "name": "76ers -6", "odds": 1.85 },
      { "name": "Hornets +6", "odds": 2.03 },
      { "name": "76ers -6.5", "odds": 1.92 },
      { "name": "Hornets +6.5", "odds": 1.96 },
      { "name": "76ers -7", "odds": 1.99 },
      { "name": "Hornets +7", "odds": 1.89 },
      { "name": "Over 224.5", "odds": 1.85 },
      { "name": "Under 224.5", "odds": 2.01 },
      { "name": "Over 225", "odds": 1.9 },
      { "name": "Under 225", "odds": 1.96 },
      { "name": "Over 225.5", "odds": 1.95 },
      { "name": "Under 225.5", "odds": 1.91 }
    ]
  },
  {
    "type": "NBA",
    "time": "2024-03-01 08:30:00+0800",
    "match_name": "Raptors vs Warriors",
    "team1": "Raptors",
    "team2": "Warriors",
    "main_bet_list": [
      { "name": "Raptors Winner", "odds": 1.8 },
      { "name": "Warriors Winner", "odds": 2.04 }
    ],
    "more_bet_list": [
      { "name": "Raptors -1.5", "odds": 1.91 },
      { "name": "Warriors +1.5", "odds": 1.97 },
      { "name": "Raptors -2", "odds": 1.98 },
      { "name": "Warriors +2", "odds": 1.9 },
      { "name": "Raptors -2.5", "odds": 2.05 },
      { "name": "Warriors +2.5", "odds": 1.83 },
      { "name": "Over 222.5", "odds": 1.97 },
      { "name": "Under 222.5", "odds": 1.89 },
      { "name": "Over 223", "odds": 2.02 },
      { "name": "Under 223", "odds": 1.84 },
      { "name": "Over 223.5", "odds": 2.07 },
      { "name": "Under 223.5", "odds": 1.79 }
    ]
  },
  {
    "type": "NBA",
    "time": "2024-03-01 08:30:00+0800",
    "match_name": "Celtics vs Mavericks",
    "team1": "Celtics",
    "team2": "Mavericks",
    "main_bet_list": [
      { "name": "Celtics Winner", "odds": 2.56 },
      { "name": "Mavericks Winner", "odds": 1.44 }
    ],
    "more_bet_list": [
      { "name": "Celtics +4.5", "odds": 2.01 },
      { "name": "Mavericks -4.5", "odds": 1.87 },
      { "name": "Celtics +5", "odds": 1.94 },
      { "name": "Mavericks -5", "odds": 1.94 },
      { "name": "Celtics +5.5", "odds": 1.87 },
      { "name": "Mavericks -5.5", "odds": 2.01 },
      { "name": "Over 221.5", "odds": 1.91 },
      { "name": "Under 221.5", "odds": 1.95 },
      { "name": "Over 222", "odds": 1.96 },
      { "name": "Under 222", "odds": 1.9 },
      { "name": "Over 222.5", "odds": 2.01 },
      { "name": "Under 222.5", "odds": 1.85 }
    ]
  },
  {
    "type": "NBA",
    "time": "2024-03-01 09:00:00+0800",
    "match_name": "Grizzlies vs Trail Blazers",
    "team1": "Grizzlies",
    "team2": "Trail Blazers",
    "main_bet_list": [
      { "name": "Grizzlies Winner", "odds": 5.54 },
      { "name": "Trail Blazers Winner", "odds": 1.02 }
    ],
    "more_bet_list": [
      { "name": "Grizzlies +11", "odds": 2.05 },
      { "name": "Trail Blazers -11", "odds": 1.83 },
      { "name": "Grizzlies +11.5", "odds": 1.96 },
      { "name": "Trail Blazers -11.5", "odds": 1.92 },
      { "name": "Grizzlies +12", "odds": 1.89 },
      { "name": "Trail Blazers -12", "odds": 1.99 },
      { "name": "Over 236.5", "odds": 1.88 },
      { "name": "Under 236.5", "odds": 1.98 },
      { "name": "Over 237", "odds": 1.93 },
      { "name": "Under 237", "odds": 1.93 },
      { "name": "Over 237.5", "odds": 1.98 },
      { "name": "Under 237.5", "odds": 1.88 }
    ]
  },
  {
    "type": "NBA",
    "time": "2024-03-01 09:00:00+0800",
    "match_name": "Timberwolves vs Kings",
    "team1": "Timberwolves",
    "team2": "Kings",
    "main_bet_list": [
      { "name": "Timberwolves Winner", "odds": 1.28 },
      { "name": "Kings Winner", "odds": 3.85 }
    ],
    "more_bet_list": [
      { "name": "Timberwolves -8", "odds": 1.87 },
      { "name": "Kings +8", "odds": 2.01 },
      { "name": "Timberwolves -8.5", "odds": 1.94 },
      { "name": "Kings +8.5", "odds": 1.94 },
      { "name": "Timberwolves -9", "odds": 2.01 },
      { "name": "Kings +9", "odds": 1.87 },
      { "name": "Over 233", "odds": 1.97 },
      { "name": "Under 233", "odds": 1.89 },
      { "name": "Over 233.5", "odds": 2.02 },
      { "name": "Under 233.5", "odds": 1.84 },
      { "name": "Over 234", "odds": 2.07 },
      { "name": "Under 234", "odds": 1.79 }
    ]
  },
  {
    "type": "NBA",
    "time": "2024-03-01 09:00:00+0800",
    "match_name": "Pelicans vs Pacers",
    "team1": "Pelicans",
    "team2": "Pacers",
    "main_bet_list": [
      { "name": "Pelicans Winner", "odds": 1.46 },
      { "name": "Pacers Winner", "odds": 2.61 }
    ],
    "more_bet_list": [
      { "name": "Pelicans -4.5", "odds": 1.89 },
      { "name": "Pacers +4.5", "odds": 1.99 },
      { "name": "Pelicans -5", "odds": 1.96 },
      { "name": "Pacers +5", "odds": 1.92 },
      { "name": "Pelicans -5.5", "odds": 2.03 },
      { "name": "Pacers +5.5", "odds": 1.85 },
      { "name": "Over 213.5", "odds": 1.88 },
      { "name": "Under 213.5", "odds": 1.98 },
      { "name": "Over 214", "odds": 1.93 },
      { "name": "Under 214", "odds": 1.93 },
      { "name": "Over 214.5", "odds": 1.98 },
      { "name": "Under 214.5", "odds": 1.88 }
    ]
  },
  {
    "type": "NBA",
    "time": "2024-03-01 11:00:00+0800",
    "match_name": "Bulls vs Bucks",
    "team1": "Bulls",
    "team2": "Bucks",
    "main_bet_list": [
      { "name": "Bulls Winner", "odds": 1.24 },
      { "name": "Bucks Winner", "odds": 4.22 }
    ],
    "more_bet_list": [
      { "name": "Bulls -9", "odds": 1.87 },
      { "name": "Bucks +9", "odds": 2.01 },
      { "name": "Bulls -9.5", "odds": 1.94 },
      { "name": "Bucks +9.5", "odds": 1.94 },
      { "name": "Bulls -10", "odds": 2.01 },
      { "name": "Bucks +10", "odds": 1.87 },
      { "name": "Over 243", "odds": 1.91 },
      { "name": "Under 243", "odds": 1.95 },
      { "name": "Over 243.5", "odds": 1.96 },
      { "name": "Under 243.5", "odds": 1.9 },
      { "name": "Over 244", "odds": 2.01 },
      { "name": "Under 244", "odds": 1.85 }
    ]
  },
  {
    "type": "NBA",
    "time": "2024-03-01 11:30:00+0800",
    "match_name": "Clippers vs Wizards",
    "team1": "Clippers",
    "team2": "Wizards",
    "main_bet_list": [
      { "name": "Clippers Winner", "odds": 1.2 },
      { "name": "Wizards Winner", "odds": 3.5 }
    ],
    "more_bet_list": [
      { "name": "Clippers -10.5", "odds": 1.93 },
      { "name": "Wizards +10.5", "odds": 1.95 },
      { "name": "Clippers -11", "odds": 2.0 },
      { "name": "Wizards +11", "odds": 1.88 },
      { "name": "Clippers -11.5", "odds": 2.07 },
      { "name": "Wizards +11.5", "odds": 1.81 },
      { "name": "Over 225", "odds": 1.88 },
      { "name": "Under 225", "odds": 1.98 },
      { "name": "Over 225.5", "odds": 1.93 },
      { "name": "Under 225.5", "odds": 1.93 },
      { "name": "Over 226", "odds": 1.98 },
      { "name": "Under 226", "odds": 1.88 }
    ]
  },
  {
    "type": "NBA",
    "time": "2024-02-28 11:00:00+0800",
    "match_name": "Thunder vs Rockets",
    "team1": "Thunder",
    "team2": "Rockets",
    "main_bet_list": [
      { "name": "Thunder Winner", "odds": 1.22 },
      { "name": "Rockets Winner", "odds": 3.38 }
    ],
    "more_bet_list": [
      { "name": "Thunder -9.5", "odds": 1.87 },
      { "name": "Rockets +9.5", "odds": 2.01 },
      { "name": "Thunder -10", "odds": 1.94 },
      { "name": "Rockets +10", "odds": 1.94 },
      { "name": "Thunder -10.5", "odds": 2.01 },
      { "name": "Rockets +10.5", "odds": 1.87 },
      { "name": "Over 235", "odds": 1.9 },
      { "name": "Under 235", "odds": 1.96 },
      { "name": "Over 235.5", "odds": 1.95 },
      { "name": "Under 235.5", "odds": 1.91 },
      { "name": "Over 236", "odds": 2.0 },
      { "name": "Under 236", "odds": 1.86 }
    ]
  },
  {
    "type": "NBA",
    "time": "2024-02-28 11:00:00+0800",
    "match_name": "Trail Blazers vs Heat",
    "team1": "Trail Blazers",
    "team2": "Heat",
    "main_bet_list": [
      { "name": "Trail Blazers Winner", "odds": 3.27 },
      { "name": "Heat Winner", "odds": 1.24 }
    ],
    "more_bet_list": [
      { "name": "Trail Blazers +6.5", "odds": 2.03 },
      { "name": "Heat -6.5", "odds": 1.85 },
      { "name": "Trail Blazers +7", "odds": 1.96 },
      { "name": "Heat -7", "odds": 1.92 },
      { "name": "Trail Blazers +7.5", "odds": 1.89 },
      { "name": "Heat -7.5", "odds": 1.99 },
      { "name": "Over 212", "odds": 1.88 },
      { "name": "Under 212", "odds": 1.98 },
      { "name": "Over 212.5", "odds": 1.93 },
      { "name": "Under 212.5", "odds": 1.93 },
      { "name": "Over 213", "odds": 1.98 },
      { "name": "Under 213", "odds": 1.88 }
    ]
  },
  {
    "type": "NBA",
    "time": "2024-02-23 11:00:00+0800",
    "match_name": "Kings vs Spurs",
    "team1": "Kings",
    "team2": "Spurs",
    "main_bet_list": [
      { "name": "Kings Winner", "odds": 1.26 },
      { "name": "Spurs Winner", "odds": 3.17 }
    ],
    "more_bet_list": [
      { "name": "Kings -8.5", "odds": 1.81 },
      { "name": "Spurs +8.5", "odds": 2.07 },
      { "name": "Kings -9", "odds": 1.88 },
      { "name": "Spurs +9", "odds": 2.0 },
      { "name": "Kings -9.5", "odds": 1.95 },
      { "name": "Spurs +9.5", "odds": 1.93 },
      { "name": "Over 240", "odds": 1.89 },
      { "name": "Under 240", "odds": 1.97 },
      { "name": "Over 240.5", "odds": 1.94 },
      { "name": "Under 240.5", "odds": 1.92 },
      { "name": "Over 241", "odds": 1.99 },
      { "name": "Under 241", "odds": 1.87 }
    ]
  },

  {
    "type": "NBA",
    "time": "2024-02-15 11:00:00+0800",
    "match_name": "Warriors vs Clippers",
    "team1": "Warriors",
    "team2": "Clippers",
    "main_bet_list": [
      { "name": "Warriors Winner", "odds": 1.68 },
      { "name": "Clippers Winner", "odds": 2.13 }
    ],
    "more_bet_list": [
      { "name": "Warriors -2.5", "odds": 1.87 },
      { "name": "Clippers +2.5", "odds": 2.01 },
      { "name": "Warriors -3", "odds": 1.94 },
      { "name": "Clippers +3", "odds": 1.94 },
      { "name": "Warriors -3.5", "odds": 2.01 },
      { "name": "Clippers +3.5", "odds": 1.87 },
      { "name": "Over 233.5", "odds": 1.88 },
      { "name": "Under 233.5", "odds": 1.98 },
      { "name": "Over 234", "odds": 1.93 },
      { "name": "Under 234", "odds": 1.93 },
      { "name": "Over 234.5", "odds": 1.98 },
      { "name": "Under 234.5", "odds": 1.88 }
    ]
  }
]
