[
  {
    "type": "Soccer",
    "time": "2023-12-17 22:00:00+0800",
    "match_name": "Brentford vs Aston Villa",
    "team1": "Brentford",
    "team2": "Aston Villa",
    "main_bet_list": [
      { "name": "Brentford Winner", "odds": 3.1 },
      { "name": "Draw", "odds": 3.55 },
      { "name": "Aston Villa Winner", "odds": 2.23 }
    ],
    "more_bet_list": [
      { "name": "Brentford +0", "odds": 2.26 },
      { "name": "Aston Villa -0", "odds": 1.66 },
      { "name": "Brentford +0.25", "odds": 1.95 },
      { "name": "Aston Villa -0.25", "odds": 1.97 },
      { "name": "Brentford +0.5", "odds": 1.73 },
      { "name": "Aston Villa -0.5", "odds": 2.19 },
      { "name": "Brentford +0.75", "odds": 1.57 },
      { "name": "Aston Villa -0.75", "odds": 2.35 },
      { "name": "Over 2.25", "odds": 1.6 },
      { "name": "Under 2.25", "odds": 2.3 },
      { "name": "Over 2.5", "odds": 1.8 },
      { "name": "Under 2.5", "odds": 2.1 },
      { "name": "Over 2.75", "odds": 2.04 },
      { "name": "Under 2.75", "odds": 1.86 },
      { "name": "Over 3", "odds": 2.25 },
      { "name": "Under 3", "odds": 1.65 }
    ]
  },
  {
    "type": "Soccer",
    "time": "2023-12-17 22:00:00+0800",
    "match_name": "Arsenal vs Brighton",
    "team1": "Arsenal",
    "team2": "Brighton",
    "main_bet_list": [
      { "name": "Arsenal Winner", "odds": 1.44 },
      { "name": "Draw", "odds": 4.6 },
      { "name": "Brighton Winner", "odds": 7.1 }
    ],
    "more_bet_list": [
      { "name": "Arsenal -0.75", "odds": 1.57 },
      { "name": "Brighton +0.75", "odds": 2.35 },
      { "name": "Arsenal -1", "odds": 1.77 },
      { "name": "Brighton +1", "odds": 2.15 },
      { "name": "Arsenal -1.25", "odds": 2.04 },
      { "name": "Brighton +1.25", "odds": 1.88 },
      { "name": "Arsenal -1.5", "odds": 2.25 },
      { "name": "Brighton +1.5", "odds": 1.67 },
      { "name": "Over 2.5", "odds": 1.62 },
      { "name": "Under 2.5", "odds": 2.28 },
      { "name": "Over 2.75", "odds": 1.76 },
      { "name": "Under 2.75", "odds": 2.14 },
      { "name": "Over 3", "odds": 2.01 },
      { "name": "Under 3", "odds": 1.89 },
      { "name": "Over 3.25", "odds": 2.22 },
      { "name": "Under 3.25", "odds": 1.68 }
    ]
  },
  {
    "type": "Soccer",
    "time": "2023-12-17 22:00:00+0800",
    "match_name": "West Ham vs Wolves",
    "team1": "West Ham",
    "team2": "Wolves",
    "main_bet_list": [
      { "name": "West Ham Winner", "odds": 2.12 },
      { "name": "Draw", "odds": 3.5 },
      { "name": "Wolves Winner", "odds": 3.45 }
    ],
    "more_bet_list": [
      { "name": "West Ham -0", "odds": 1.58 },
      { "name": "Wolves +0", "odds": 2.34 },
      { "name": "West Ham -0.25", "odds": 1.83 },
      { "name": "Wolves +0.25", "odds": 2.09 },
      { "name": "West Ham -0.5", "odds": 2.11 },
      { "name": "Wolves +0.5", "odds": 1.81 },
      { "name": "West Ham -0.75", "odds": 2.31 },
      { "name": "Wolves +0.75", "odds": 1.61 },
      { "name": "Over 2.25", "odds": 1.68 },
      { "name": "Under 2.25", "odds": 2.22 },
      { "name": "Over 2.5", "odds": 1.94 },
      { "name": "Under 2.5", "odds": 1.96 },
      { "name": "Over 2.75", "odds": 2.14 },
      { "name": "Under 2.75", "odds": 1.76 },
      { "name": "Over 3", "odds": 2.38 },
      { "name": "Under 3", "odds": 1.52 }
    ]
  },
  {
    "type": "Soccer",
    "time": "2023-12-18 00:30:00+0800",
    "match_name": "Liverpool vs Man United",
    "team1": "Liverpool",
    "team2": "Man United",
    "main_bet_list": [
      { "name": "Liverpool Winner", "odds": 1.39 },
      { "name": "Draw", "odds": 5.2 },
      { "name": "Man United Winner", "odds": 7.2 }
    ],
    "more_bet_list": [
      { "name": "Liverpool -1", "odds": 1.56 },
      { "name": "Man United +1", "odds": 2.36 },
      { "name": "Liverpool -1.25", "odds": 1.82 },
      { "name": "Man United +1.25", "odds": 2.1 },
      { "name": "Liverpool -1.5", "odds": 2.04 },
      { "name": "Man United +1.5", "odds": 1.88 },
      { "name": "Liverpool -1.75", "odds": 2.21 },
      { "name": "Man United +1.75", "odds": 1.71 },
      { "name": "Over 3.25", "odds": 1.75 },
      { "name": "Under 3.25", "odds": 2.15 },
      { "name": "Over 3.5", "odds": 2.02 },
      { "name": "Under 3.5", "odds": 1.88 },
      { "name": "Over 3.75", "odds": 2.13 },
      { "name": "Under 3.75", "odds": 1.77 },
      { "name": "Over 4", "odds": 2.41 },
      { "name": "Under 4", "odds": 1.49 }
    ]
  },
  {
    "type": "Soccer",
    "time": "2023-12-17 22:00:00+0800",
    "match_name": "Udinese vs Sassuolo",
    "team1": "Udinese",
    "team2": "Sassuolo",
    "main_bet_list": [
      { "name": "Udinese Winner", "odds": 2.33 },
      { "name": "Draw", "odds": 3.55 },
      { "name": "Sassuolo Winner", "odds": 2.95 }
    ],
    "more_bet_list": [
      { "name": "Udinese +0", "odds": 1.68 },
      { "name": "Sassuolo -0", "odds": 2.24 },
      { "name": "Udinese +0.25", "odds": 1.56 },
      { "name": "Sassuolo -0.25", "odds": 2.37 },
      { "name": "Udinese -0.25", "odds": 2.08 },
      { "name": "Sassuolo +0.25", "odds": 1.85 },
      { "name": "Udinese -0.5", "odds": 2.25 },
      { "name": "Sassuolo +0.5", "odds": 1.68 },
      { "name": "Over 2.5", "odds": 1.74 },
      { "name": "Under 2.5", "odds": 2.16 },
      { "name": "Over 2.75", "odds": 1.97 },
      { "name": "Under 2.75", "odds": 1.93 },
      { "name": "Over 3", "odds": 2.19 },
      { "name": "Under 3", "odds": 1.71 },
      { "name": "Over 3.25", "odds": 2.34 },
      { "name": "Under 3.25", "odds": 1.56 }
    ]
  },
  {
    "type": "Soccer",
    "time": "2023-12-17 22:00:00+0800",
    "match_name": "Fiorentina vs Verona",
    "team1": "Fiorentina",
    "team2": "Verona",
    "main_bet_list": [
      { "name": "Fiorentina Winner", "odds": 1.46 },
      { "name": "Draw", "odds": 4.35 },
      { "name": "Verona Winner", "odds": 7.3 }
    ],
    "more_bet_list": [
      { "name": "Fiorentina -0.75", "odds": 1.59 },
      { "name": "Verona +0.75", "odds": 2.34 },
      { "name": "Fiorentina -1", "odds": 1.78 },
      { "name": "Verona +1", "odds": 2.15 },
      { "name": "Fiorentina -1.25", "odds": 2.07 },
      { "name": "Verona +1.25", "odds": 1.86 },
      { "name": "Fiorentina -1.5", "odds": 2.29 },
      { "name": "Verona +1.5", "odds": 1.64 },
      { "name": "Over 2.25", "odds": 1.64 },
      { "name": "Under 2.25", "odds": 2.26 },
      { "name": "Over 2.5", "odds": 1.88 },
      { "name": "Under 2.5", "odds": 2.02 },
      { "name": "Over 2.75", "odds": 2.1 },
      { "name": "Under 2.75", "odds": 1.8 },
      { "name": "Over 3", "odds": 2.31 },
      { "name": "Under 3", "odds": 1.59 }
    ]
  },
  {
    "type": "Soccer",
    "time": "2023-12-18 01:00:00+0800",
    "match_name": "Bologna vs Roma",
    "team1": "Bologna",
    "team2": "Roma",
    "main_bet_list": [
      { "name": "Bologna Winner", "odds": 2.49 },
      { "name": "Draw", "odds": 2.94 },
      { "name": "Roma Winner", "odds": 3.25 }
    ],
    "more_bet_list": [
      { "name": "Bologna -0", "odds": 1.69 },
      { "name": "Roma +0", "odds": 2.24 },
      { "name": "Bologna +0.25", "odds": 1.48 },
      { "name": "Roma -0.25", "odds": 2.45 },
      { "name": "Bologna -0.25", "odds": 2.06 },
      { "name": "Roma +0.25", "odds": 1.87 },
      { "name": "Bologna -0.5", "odds": 2.33 },
      { "name": "Roma +0.5", "odds": 1.6 },
      { "name": "Over 1.5", "odds": 1.6 },
      { "name": "Under 1.5", "odds": 2.3 },
      { "name": "Over 1.75", "odds": 1.73 },
      { "name": "Under 1.75", "odds": 2.17 },
      { "name": "Over 2", "odds": 2.1 },
      { "name": "Under 2", "odds": 1.8 },
      { "name": "Over 2.25", "odds": 2.32 },
      { "name": "Under 2.25", "odds": 1.58 }
    ]
  },
  {
    "type": "Soccer",
    "time": "2023-12-17 21:00:00+0800",
    "match_name": "Almeria vs Mallorca",
    "team1": "Almeria",
    "team2": "Mallorca",
    "main_bet_list": [
      { "name": "Almeria Winner", "odds": 2.42 },
      { "name": "Draw", "odds": 3.2 },
      { "name": "Mallorca Winner", "odds": 3.2 }
    ],
    "more_bet_list": [
      { "name": "Almeria +0", "odds": 1.68 },
      { "name": "Mallorca -0", "odds": 2.26 },
      { "name": "Almeria +0.25", "odds": 1.51 },
      { "name": "Mallorca -0.25", "odds": 2.43 },
      { "name": "Almeria -0.25", "odds": 2.05 },
      { "name": "Mallorca +0.25", "odds": 1.89 },
      { "name": "Almeria -0.5", "odds": 2.3 },
      { "name": "Mallorca +0.5", "odds": 1.64 },
      { "name": "Over 1.75", "odds": 1.59 },
      { "name": "Under 1.75", "odds": 2.33 },
      { "name": "Over 2", "odds": 1.79 },
      { "name": "Under 2", "odds": 2.13 },
      { "name": "Over 2.25", "odds": 2.11 },
      { "name": "Under 2.25", "odds": 1.81 },
      { "name": "Over 2.5", "odds": 2.29 },
      { "name": "Under 2.5", "odds": 1.63 }
    ]
  },
  {
    "type": "Soccer",
    "time": "2023-12-17 23:15:00+0800",
    "match_name": "Real Sociedad vs Real Betis",
    "team1": "Real Sociedad",
    "team2": "Real Betis",
    "main_bet_list": [
      { "name": "Real Sociedad Winner", "odds": 1.57 },
      { "name": "Draw", "odds": 3.9 },
      { "name": "Real Betis Winner", "odds": 6.4 }
    ],
    "more_bet_list": [
      { "name": "Real Sociedad -0.5", "odds": 1.57 },
      { "name": "Real Betis +0.5", "odds": 2.36 },
      { "name": "Real Sociedad -0.75", "odds": 1.69 },
      { "name": "Real Betis +0.75", "odds": 2.24 },
      { "name": "Real Sociedad -1", "odds": 1.98 },
      { "name": "Real Betis +1", "odds": 1.95 },
      { "name": "Real Sociedad -1.25", "odds": 2.29 },
      { "name": "Real Betis +1.25", "odds": 1.64 },
      { "name": "Over 2", "odds": 1.61 },
      { "name": "Under 2", "odds": 2.31 },
      { "name": "Over 2.25", "odds": 1.8 },
      { "name": "Under 2.25", "odds": 2.12 },
      { "name": "Over 2.5", "odds": 2.01 },
      { "name": "Under 2.5", "odds": 1.91 },
      { "name": "Over 2.75", "odds": 2.27 },
      { "name": "Under 2.75", "odds": 1.63 }
    ]
  },
  {
    "type": "Soccer",
    "time": "2023-12-18 01:30:00+0800",
    "match_name": "Las Palmas vs Cadiz",
    "team1": "Las Palmas",
    "team2": "Cadiz",
    "main_bet_list": [
      { "name": "Las Palmas Winner", "odds": 2.03 },
      { "name": "Draw", "odds": 3.2 },
      { "name": "Cadiz Winner", "odds": 4.1 }
    ],
    "more_bet_list": [
      { "name": "Las Palmas -0.25", "odds": 1.71 },
      { "name": "Cadiz +0.25", "odds": 2.22 },
      { "name": "Las Palmas -0.5", "odds": 2.03 },
      { "name": "Cadiz +0.5", "odds": 1.9 },
      { "name": "Las Palmas -0.75", "odds": 2.25 },
      { "name": "Cadiz +0.75", "odds": 1.68 },
      { "name": "Las Palmas -1", "odds": 2.53 },
      { "name": "Cadiz +1", "odds": 1.4 },
      { "name": "Over 1.75", "odds": 1.61 },
      { "name": "Under 1.75", "odds": 2.29 },
      { "name": "Over 2", "odds": 1.87 },
      { "name": "Under 2", "odds": 2.03 },
      { "name": "Over 2.25", "odds": 2.15 },
      { "name": "Under 2.25", "odds": 1.75 },
      { "name": "Over 2.5", "odds": 2.31 },
      { "name": "Under 2.5", "odds": 1.59 }
    ]
  },
  {
    "type": "Soccer",
    "time": "2023-12-18 04:00:00+0800",
    "match_name": "Real Madrid vs Villarreal",
    "team1": "Real Madrid",
    "team2": "Villarreal",
    "main_bet_list": [
      { "name": "Real Madrid Winner", "odds": 3.0 },
      { "name": "Draw", "odds": 4.0 },
      { "name": "Villarreal Winner", "odds": 2.14 }
    ],
    "more_bet_list": [
      { "name": "Real Madrid +0", "odds": 2.3 },
      { "name": "Villarreal -0", "odds": 1.64 },
      { "name": "Real Madrid +0.25", "odds": 2.03 },
      { "name": "Villarreal -0.25", "odds": 1.91 },
      { "name": "Real Madrid +0.5", "odds": 1.81 },
      { "name": "Villarreal -0.5", "odds": 2.13 },
      { "name": "Real Madrid +0.75", "odds": 1.62 },
      { "name": "Villarreal -0.75", "odds": 2.32 },
      { "name": "Over 2.75", "odds": 1.62 },
      { "name": "Under 2.75", "odds": 2.3 },
      { "name": "Over 3", "odds": 1.79 },
      { "name": "Under 3", "odds": 2.13 },
      { "name": "Over 3.25", "odds": 2.02 },
      { "name": "Under 3.25", "odds": 1.9 },
      { "name": "Over 3.5", "odds": 2.25 },
      { "name": "Under 3.5", "odds": 1.67 }
    ]
  },
  {
    "type": "Soccer",
    "time": "2023-12-16 22:30:00+0800",
    "match_name": "Mainz vs Heidenheim",
    "team1": "Mainz",
    "team2": "Heidenheim",
    "main_bet_list": [
      { "name": "Mainz Winner", "odds": 1.7 },
      { "name": "Draw", "odds": 4.05 },
      { "name": "Heidenheim Winner", "odds": 4.65 }
    ],
    "more_bet_list": [
      { "name": "Mainz -0.5", "odds": 1.7 },
      { "name": "Heidenheim +0.5", "odds": 2.24 },
      { "name": "Mainz -0.75", "odds": 1.92 },
      { "name": "Heidenheim +0.75", "odds": 2.02 },
      { "name": "Mainz -1", "odds": 2.21 },
      { "name": "Heidenheim +1", "odds": 1.73 },
      { "name": "Mainz -1.25", "odds": 2.36 },
      { "name": "Heidenheim +1.25", "odds": 1.58 },
      { "name": "Over 2.5", "odds": 1.7 },
      { "name": "Under 2.5", "odds": 2.22 },
      { "name": "Over 2.75", "odds": 1.87 },
      { "name": "Under 2.75", "odds": 2.05 },
      { "name": "Over 3", "odds": 2.18 },
      { "name": "Under 3", "odds": 1.74 },
      { "name": "Over 3.25", "odds": 2.34 },
      { "name": "Under 3.25", "odds": 1.58 }
    ]
  },
  {
    "type": "Soccer",
    "time": "2023-12-17 01:30:00+0800",
    "match_name": "RB Leipzig vs Hoffenheim",
    "team1": "RB Leipzig",
    "team2": "Hoffenheim",
    "main_bet_list": [
      { "name": "RB Leipzig Winner", "odds": 1.39 },
      { "name": "Draw", "odds": 5.2 },
      { "name": "Hoffenheim Winner", "odds": 7.3 }
    ],
    "more_bet_list": [
      { "name": "RB Leipzig -1", "odds": 1.55 },
      { "name": "Hoffenheim +1", "odds": 2.39 },
      { "name": "RB Leipzig -1.25", "odds": 1.77 },
      { "name": "Hoffenheim +1.25", "odds": 2.17 },
      { "name": "RB Leipzig -1.5", "odds": 2.02 },
      { "name": "Hoffenheim +1.5", "odds": 1.92 },
      { "name": "RB Leipzig -1.75", "odds": 2.22 },
      { "name": "Hoffenheim +1.75", "odds": 1.72 },
      { "name": "Over 3.25", "odds": 1.74 },
      { "name": "Under 3.25", "odds": 2.18 },
      { "name": "Over 3.5", "odds": 1.97 },
      { "name": "Under 3.5", "odds": 1.95 },
      { "name": "Over 3.75", "odds": 2.2 },
      { "name": "Under 3.75", "odds": 1.72 },
      { "name": "Over 4", "odds": 2.36 },
      { "name": "Under 4", "odds": 1.56 }
    ]
  },
  {
    "type": "Soccer",
    "time": "2023-12-15 04:00:00+0800",
    "match_name": "West Ham vs SC Freiburg",
    "team1": "West Ham",
    "team2": "SC Freiburg",
    "main_bet_list": [
      { "name": "West Ham Winner", "odds": 1.94 },
      { "name": "Draw", "odds": 3.8 },
      { "name": "SC Freiburg Winner", "odds": 3.7 }
    ],
    "more_bet_list": [
      { "name": "West Ham -0.25", "odds": 1.7 },
      { "name": "SC Freiburg +0.25", "odds": 2.22 },
      { "name": "West Ham -0.5", "odds": 1.94 },
      { "name": "SC Freiburg +0.5", "odds": 1.98 },
      { "name": "West Ham -0.75", "odds": 2.19 },
      { "name": "SC Freiburg +0.75", "odds": 1.73 },
      { "name": "West Ham -1", "odds": 2.43 },
      { "name": "SC Freiburg +1", "odds": 1.49 },
      { "name": "Over 2.25", "odds": 1.53 },
      { "name": "Under 2.25", "odds": 2.37 },
      { "name": "Over 2.5", "odds": 1.75 },
      { "name": "Under 2.5", "odds": 2.15 },
      { "name": "Over 2.75", "odds": 1.93 },
      { "name": "Under 2.75", "odds": 1.97 },
      { "name": "Over 3", "odds": 2.2 },
      { "name": "Under 3", "odds": 1.7 }
    ]
  },

  {
    "type": "Soccer",
    "time": "2023-12-15 04:00:00+0800",
    "match_name": "Sporting vs SK Sturm Graz",
    "team1": "Sporting",
    "team2": "SK Sturm Graz",
    "main_bet_list": [
      { "name": "Sporting Winner", "odds": 1.71 },
      { "name": "Draw", "odds": 3.95 },
      { "name": "SK Sturm Graz Winner", "odds": 4.7 }
    ],
    "more_bet_list": [
      { "name": "Sporting -0.5", "odds": 1.71 },
      { "name": "SK Sturm Graz +0.5", "odds": 2.21 },
      { "name": "Sporting -0.75", "odds": 1.91 },
      { "name": "SK Sturm Graz +0.75", "odds": 2.01 },
      { "name": "Sporting -1", "odds": 2.19 },
      { "name": "SK Sturm Graz +1", "odds": 1.73 },
      { "name": "Sporting -1.25", "odds": 2.38 },
      { "name": "SK Sturm Graz +1.25", "odds": 1.54 },
      { "name": "Over 2.25", "odds": 1.58 },
      { "name": "Under 2.25", "odds": 2.32 },
      { "name": "Over 2.5", "odds": 1.76 },
      { "name": "Under 2.5", "odds": 2.14 },
      { "name": "Over 2.75", "odds": 2.0 },
      { "name": "Under 2.75", "odds": 1.9 },
      { "name": "Over 3", "odds": 2.2 },
      { "name": "Under 3", "odds": 1.7 }
    ]
  },
  {
    "type": "Soccer",
    "time": "2023-12-15 04:00:00+0800",
    "match_name": "Rakow Czestochowa vs Atalanta",
    "team1": "Rakow Czestochowa",
    "team2": "Atalanta",
    "main_bet_list": [
      { "name": "Rakow Czestochowa Winner", "odds": 2.06 },
      { "name": "Draw", "odds": 3.5 },
      { "name": "Atalanta Winner", "odds": 3.6 }
    ],
    "more_bet_list": [
      { "name": "Rakow Czestochowa -0.25", "odds": 1.77 },
      { "name": "Atalanta +0.25", "odds": 2.13 },
      { "name": "Rakow Czestochowa -0.5", "odds": 2.04 },
      { "name": "Atalanta +0.5", "odds": 1.86 },
      { "name": "Rakow Czestochowa -0.75", "odds": 2.3 },
      { "name": "Atalanta +0.75", "odds": 1.6 },
      { "name": "Over 2.25", "odds": 1.73 },
      { "name": "Under 2.25", "odds": 2.15 },
      { "name": "Over 2.5", "odds": 2.0 },
      { "name": "Under 2.5", "odds": 1.88 },
      { "name": "Over 2.75", "odds": 2.18 },
      { "name": "Under 2.75", "odds": 1.7 }
    ]
  }
]
